{
  "episode_number": 0,
  "title": "Experimental evaluation of two-layer air bubble curtains to prevent seawater intrusion into rivers",
  "paper_url": "https://iwaponline.com/jwcc/article/14/2/543/92985/Experimental-evaluation-of-two-layer-air-bubble",
  "filename": "ep000.mp3",
  "published_at": "2026-03-22T20:54:00.598861+00:00",
  "file_size_bytes": 32196401,
  "duration_seconds": 0,
  "description": "SpeakForWater Episode 0: Experimental evaluation of two-layer air bubble curtains to prevent seawater intrusion into rivers. A podcast conversation between Anna and Ehsan discussing the latest water resources research."
}